<annotation>
	<folder>images</folder>
	<filename>dlwkigk3_720_2022-07-19_19-59_output_0.jpeg</filename>
	<path>C:\Users\gogol\Desktop\Purba\2022-07-19 Purba\images\dlwkigk3_720_2022-07-19_19-59_output_0.jpeg</path>
	<source>
		<database>Unknown</database>
	</source>
	<size>
		<width>1280</width>
		<height>720</height>
		<depth>3</depth>
	</size>
	<segmented>0</segmented>
	<object>
		<name>sea</name>
		<pose>Unspecified</pose>
		<truncated>0</truncated>
		<difficult>0</difficult>
		<bndbox>
			<xmin>671</xmin>
			<ymin>318</ymin>
			<xmax>685</xmax>
			<ymax>334</ymax>
		</bndbox>
	</object>
	<object>
		<name>human</name>
		<pose>Unspecified</pose>
		<truncated>0</truncated>
		<difficult>0</difficult>
		<bndbox>
			<xmin>207</xmin>
			<ymin>611</ymin>
			<xmax>217</xmax>
			<ymax>623</ymax>
		</bndbox>
	</object>
	<object>
		<name>human</name>
		<pose>Unspecified</pose>
		<truncated>0</truncated>
		<difficult>0</difficult>
		<bndbox>
			<xmin>598</xmin>
			<ymin>556</ymin>
			<xmax>603</xmax>
			<ymax>564</ymax>
		</bndbox>
	</object>
	<object>
		<name>human</name>
		<pose>Unspecified</pose>
		<truncated>0</truncated>
		<difficult>0</difficult>
		<bndbox>
			<xmin>588</xmin>
			<ymin>554</ymin>
			<xmax>593</xmax>
			<ymax>564</ymax>
		</bndbox>
	</object>
	<object>
		<name>sea</name>
		<pose>Unspecified</pose>
		<truncated>0</truncated>
		<difficult>0</difficult>
		<bndbox>
			<xmin>713</xmin>
			<ymin>590</ymin>
			<xmax>743</xmax>
			<ymax>604</ymax>
		</bndbox>
	</object>
</annotation>
