<annotation>
    <folder>dataset-processing</folder>
    <filename>dlwkigk3_720_2022-07-19_05-58_output_0.xml</filename>
    <path>C:\Users\Daniel Ahlers\Git\dataset-processing\dlwkigk3_720_2022-07-19_05-58_output_0.xml</path>
    <source>
        <database>Unknown</database>
    </source>
    <size>
        <width>1280</width>
        <height>720</height>
        <depth>3</depth>
    </size>
    <segmented>0</segmented>
    <object>
        <name>sea</name>
        <pose>Unspecified</pose>
        <truncated>0</truncated>
        <difficult>0</difficult>
        <bndbox>
            <xmin>8</xmin>
            <ymin>516</ymin>
            <xmax>193</xmax>
            <ymax>627</ymax>
        </bndbox>
    </object>    <object>
        <name>sea</name>
        <pose>Unspecified</pose>
        <truncated>0</truncated>
        <difficult>0</difficult>
        <bndbox>
            <xmin>338</xmin>
            <ymin>529</ymin>
            <xmax>388</xmax>
            <ymax>635</ymax>
        </bndbox>
    </object>    <object>
        <name>sea</name>
        <pose>Unspecified</pose>
        <truncated>0</truncated>
        <difficult>0</difficult>
        <bndbox>
            <xmin>324</xmin>
            <ymin>498</ymin>
            <xmax>358</xmax>
            <ymax>607</ymax>
        </bndbox>
    </object>    <object>
        <name>sea</name>
        <pose>Unspecified</pose>
        <truncated>0</truncated>
        <difficult>0</difficult>
        <bndbox>
            <xmin>482</xmin>
            <ymin>554</ymin>
            <xmax>517</xmax>
            <ymax>679</ymax>
        </bndbox>
    </object>    <object>
        <name>sea</name>
        <pose>Unspecified</pose>
        <truncated>0</truncated>
        <difficult>0</difficult>
        <bndbox>
            <xmin>551</xmin>
            <ymin>514</ymin>
            <xmax>601</xmax>
            <ymax>635</ymax>
        </bndbox>
    </object>    <object>
        <name>sea</name>
        <pose>Unspecified</pose>
        <truncated>0</truncated>
        <difficult>0</difficult>
        <bndbox>
            <xmin>363</xmin>
            <ymin>368</ymin>
            <xmax>374</xmax>
            <ymax>408</ymax>
        </bndbox>
    </object>    <object>
        <name>sea</name>
        <pose>Unspecified</pose>
        <truncated>0</truncated>
        <difficult>0</difficult>
        <bndbox>
            <xmin>770</xmin>
            <ymin>514</ymin>
            <xmax>790</xmax>
            <ymax>534</ymax>
        </bndbox>
    </object>    <object>
        <name>sea</name>
        <pose>Unspecified</pose>
        <truncated>0</truncated>
        <difficult>0</difficult>
        <bndbox>
            <xmin>1009</xmin>
            <ymin>367</ymin>
            <xmax>1020</xmax>
            <ymax>392</ymax>
        </bndbox>
    </object>    <object>
        <name>sea</name>
        <pose>Unspecified</pose>
        <truncated>0</truncated>
        <difficult>0</difficult>
        <bndbox>
            <xmin>1224</xmin>
            <ymin>511</ymin>
            <xmax>1280</xmax>
            <ymax>606</ymax>
        </bndbox>
    </object>    <object>
        <name>sea</name>
        <pose>Unspecified</pose>
        <truncated>0</truncated>
        <difficult>0</difficult>
        <bndbox>
            <xmin>1036</xmin>
            <ymin>421</ymin>
            <xmax>1065</xmax>
            <ymax>448</ymax>
        </bndbox>
    </object>    <object>
        <name>sea</name>
        <pose>Unspecified</pose>
        <truncated>0</truncated>
        <difficult>0</difficult>
        <bndbox>
            <xmin>1006</xmin>
            <ymin>410</ymin>
            <xmax>1039</xmax>
            <ymax>440</ymax>
        </bndbox>
    </object>
</annotation>
